{"formerly":"M3791 N1546","seq":"1,5,10,10,0,19,35,40,25,10,45,75,80,60,15,45,85,115,115,90,21,35,95,130,135,135,70,35,65,105,146,120,150,90,65,25,90,115,150,125,130,45,80,35,5,160,110,170,85,95,25,50,0,60,95,116,120,1351,-5,10,-10,0,19,-35,40,-25,-10,45,-75,80,-60,15,45,-85,115,-115,90,-21,-35,95,-130,135,-135,70,-35,-65,105,-146,120,-150,90,-65,-25,90,-115,150,-125,130,-45,80,35,-5,160,-110,170,-85,95,25,50,0,-60,95,-116,120,-135","description":"Expand {Product_{j=1..inf} (1-x^j) - 1 }^5 in powers of x.","references":["H. Gupta, On the coefficients of the powers of Dedekind's modular form, J. London Math. Soc., 39 (1964), 433-440.","N. J. A. Sloane, A Handbook of Integer Sequences, Academic Press, 1973 (includes this sequence).","N. J. A. Sloane and Simon Plouffe, The Encyclopedia of Integer Sequences, Academic Press, 1995 (includes this sequence)."],"keyword":"sign","offset":"1,2","author":"_N. J. A. Sloane_."}