{"formerly":"M4918 N2111","seq":"0,0,0,0,13,252,3740,51300,685419,9095856,120872850,1614234960,21697730835,293695935764,4003423965684,54944523689692,758990230992175,10548884795729280,147458773053913268,2072369440050644208,29271357456284966994","description":"Number of simple quadrangulations.","references":["R. C. Mullin and P. J. Schellenberg, The enumeration of c-nets via triangulations, J. Combin. Theory, 4 (1968), 259-276.","N. J. A. Sloane, A Handbook of Integer Sequences, Academic Press, 1973 (includes this sequence).","N. J. A. Sloane and Simon Plouffe, The Encyclopedia of Integer Sequences, Academic Press, 1995 (includes this sequence)."],"crossrefs":["A diagonal of A210252."],"keyword":"nonn","offset":"1,5","author":"_N. J. A. Sloane_.","extensions":["Corrected and extended by _Sean A. Irvine_, Sep 29 2015"]}