{"formerly":"M1362 N0526","seq":"1,2,5,9,18,31,57,92,159","description":"Number of allomorphic polyhedra with n nodes.","references":["M. B. Dillencourt, personal communication.","J. McClellan, The question of allomorphs, J. Rec. Math., 4 (1971), 115-123.","N. J. A. Sloane, A Handbook of Integer Sequences, Academic Press, 1973 (includes this sequence).","N. J. A. Sloane and Simon Plouffe, The Encyclopedia of Integer Sequences, Academic Press, 1995 (includes this sequence)."],"keyword":"nonn","offset":"4,2","author":"_N. J. A. Sloane_."}