{"formerly":"M0211","seq":"1,1,2,2,2,2,2,2,4,2,2,2,4,4,2,2,2,2,4,2,2,4,2,2,2,4,4,4,4,2,2,4,4,2,4,2,2,4,2,2,2,4,8,2,2,4,2,4,2,2,4,4,4,2,2,4,4,2,4,2,2,4,2,2,4,8,2,4,2,4,4,2,2,4,4,4,4,2,2,2,4,2,4,2,4,8,4,2,4,2,4,4,2,2,4,2,4,4,2,4,4,4,2,2,4","description":"Number of genera of quadratic field with discriminant -4n, where -n == 2 or 3 (mod 4).","references":["D. A. Buell, Binary Quadratic Forms. Springer-Verlag, NY, 1989, pp. 224-241.","N. J. A. Sloane and Simon Plouffe, The Encyclopedia of Integer Sequences, Academic Press, 1995 (includes this sequence)."],"links":["<a href=\"/index/Qua#quadfield\">Index entries for sequences related to quadratic fields</a>"],"crossrefs":["Cf. A003641."],"keyword":"nonn","offset":"1,3","author":"_N. J. A. Sloane_, _Mira Bernstein_"}