{"formerly":"M3734","seq":"0,0,0,0,0,0,0,0,0,0,5,2,9,1,7,7,2,1","description":"Decimal expansion of Bohr radius (meters).","references":["H. J. Fischbeck and K. Fischbeck, Formulas. Facts and Constants, Springer-Verlag, NY, 2nd ed., 1987.","K. R. Lang, Astrophysical Data: Planets and Stars, Springer-Verlag, NY, 1991.","N. J. A. Sloane and Simon Plouffe, The Encyclopedia of Integer Sequences, Academic Press, 1995 (includes this sequence)."],"links":["NIST Physics Laboratory, <a href=\"http://physics.nist.gov/cgi-bin/cuu/Value?bohrrada0\">Bohr Radius</a>.","Wikipedia, <a href=\"http://en.wikipedia.org/wiki/Bohr_radius\">Bohr radius</a>."],"example":"5.2917721092(17)*10^-11 m","keyword":"cons,nonn","offset":"0,11","author":"_N. J. A. Sloane_, _Mira Bernstein_","extensions":["Updated to conform with CODATA 2010 recommended value - _Raphie Frank_, Dec 25 2012"]}