{"formerly":"","seq":"1,2,4,8,61,23,46,821,652,215,4201,8402,6904,2918,48361,86723,63556,270131,441262,882425,6758401,2517902,4034914,8068838,61277761,23445533,46880176,827712431,654534862,219078635,4281473701,8463847412","description":"Powers of 2 written backwards.","comments":"Freeman Dyson believes that A014963(a(n))<>5 is true but cannot be proved, see link. - _Reinhard Zumkeller_, Jan 05 2005a(n) = A004086(A000079(n)). - _Reinhard Zumkeller_, Apr 02 2014","links":["T. D. Noe, <a href=\"/A004094/b004094.txt\">Table of n, a(n) for n=0..1000</a>","Richard Lipton, <a href=\"https://rjlipton.wordpress.com/2014/10/11/more-on-testing-dysons-conjecture/\">More on testing Dyson's conjecture</a> (2014)","Edge Foundation, <a href=\"http://www.edge.org/q2005/q05_9.html#dysonf\">Annual Question 2005</a>"],"prog":"(Haskell)a004094 = a004086 . a000079  -- _Reinhard Zumkeller_, Apr 02 2014(PARI) rev(n)=subst(Polrev(digits(n)),'x,10)a(n)=rev(2^n) \\\\ _Charles R Greathouse IV_, Oct 20 2014","crossrefs":["Cf. A102382, A102383, A102384, A102385."],"keyword":"nonn,base,easy","offset":"0,2","author":"_N. J. A. Sloane_.","extensions":["More terms from _Reinhard Zumkeller_, Jan 05 2005"]}