{"formerly":"M4923","seq":"14,19,47,61,75,197,742,1104,1537,2580,3684,4788,7385,7647,7909,31331,34285,34348,56604,86935,120284,129106,147640,156146,174680,183186,298320","description":"Primitive repfigit numbers.","references":["M. Keith, Repfigit Numbers, J. Recreational Math., Vol. 19, No. 2, pp. 41-42, 1987.","N. J. A. Sloane and Simon Plouffe, The Encyclopedia of Integer Sequences, Academic Press, 1995 (includes this sequence)."],"crossrefs":["Cf. A007629."],"keyword":"nonn","offset":"1,1","author":"_N. J. A. Sloane_."}