{"formerly":"","seq":"1,2,3,2,5,6,7,2,3,10,11,6,13,14,15,2,17,6,19,10,21,22,23,6,5,26,3,14,29,30,31,2,33,34,35,6,37,38,39,10,41,42,43,22,15,46,47,6,7,10,51,26,53,6,55,14,57,58,59,30,61,62,21,2,65,66,67,34,69,70,71,6,73,74,15,38,77,78","description":"Largest squarefree number dividing n: the squarefree kernel of n, rad(n), radical of n.","comments":"Multiplicative with a(p^e) = p.For n>1, product of the distinct prime factors of n.a(k)=k for k=squarefree numbers A005117. - _Lekraj Beedassy_, Sep 05 2006A note on square roots of numbers: we can write sqrt(n) = b*sqrt(c) where c is squarefree. Then b = A000188(n) is the \"inner square root\" of n, c = A007913(n), LCM(b,c) = A007947(n) = \"squarefree kernel\" of n and bc = A019554(n) = \"outer square root\" of n.a(n) = A128651(A129132(n-1) + 2) for n>1. - _Reinhard Zumkeller_, Mar 30 2007Also the least common multiple of the prime factors of n. - _Peter Luschny_, Mar 22 2011The Mobius transform of the sequence generates the sequence of absolute values of A097945. - _R. J. Mathar_, Apr 04 2011Appears to be the period length of k^n mod n. For example, n^12 mod 12 has period 6, repeating 1,4,9,4,1,0, so a(12)= 6. - _Gary Detlefs_, Apr 14 2013a(n) differs from A014963(n) when n is a term of A024619. - _Eric Desbiaux_, Mar 24 2014","links":["T. D. Noe and Daniel Forgues, <a href=\"/A007947/b007947.txt\">Table of n, a(n) for n = 1..100000</a> (first 10000 terms from T. D. Noe)","Masum Billal, <a href=\"http://arxiv.org/abs/1501.00609\">Divisible Sequence and its Characteristic Sequence</a>, arXiv:1501.00609 [math.NT], 2015, theorem 11 page 5.","Henry Bottomley, <a href=\"http://fs.gallup.unm.edu/Bottomley-Sm-Mult-Functions.htm\">Some Smarandache-type multiplicative sequences</a>","Steven R. Finch, <a href=\"http://www.people.fas.harvard.edu/~sfinch/csolve/try.pdf\">Unitarism and infinitarism</a>.","Jarosław Grytczuk, <a href=\"http://dx.doi.org/10.1016/j.disc.2007.08.039\">Thue type problems for graphs, points and numbers</a>, Discrete Math., 308 (2008), 4419-4429.","Neville Holmes, <a href=\"http://www.comp.utas.edu.au/users/nholmes/sqncs/index.htm#A007947\">Integer Sequences</a>","Serge Lang, <a href=\"http://dx.doi.org/10.1090/S0273-0979-1990-15899-9\">Old and New Conjectured Diophantine Inequalities</a>, Bull. Amer. Math. Soc., 23 (1990), 37-75. see p. 39.","D. H. Lehmer, <a href=\"http://matwbn.icm.edu.pl/ksiazki/aa/aa27/aa27121.pdf\">Euler constants for arithmetical progressions</a>, Collection of articles in memory of Juriĭ Vladimirovič Linnik. Acta Arith. 27 (1975), 125--142. MR0369233 (51 #5468). See N_k on page 131.","Ivar Peterson, <a href=\"http://web.archive.org/web/20130702061828/http://www.maa.org/mathland/mathtrek_12_8.html\">The Amazing ABC Conjecture</a>","Paul Tarau, <a href=\"http://dx.doi.org/10.1007/978-3-642-23283-1_15\">Emulating Primality with Multiset Representations of Natural Numbers</a>, in Theoretical Aspects of Computing, ICTAC 2011, Lecture Notes in Computer Science, 2011, Volume 6916/2011, 218-238","Paul Tarau, <a href=\"http://dx.doi.org/10.1016/j.tcs.2014.04.025\">Towards a generic view of primality through multiset decompositions of natural numbers</a>, Theoretical Computer Science, Volume 537, 5 June 2014, Pages 105-124.","Wikipedia, <a href=\"https://en.wikipedia.org/wiki/Radical_of_an_integer\">Radical of an integer</a>."],"formula":"n = Product (p_j^k_j) -> Product (p_j).a(n) = Product(A027748(n,k): 1 <= k <= A001221(n)). - _Reinhard Zumkeller_, Aug 27 2011Dirichlet g.f.: zeta(s)*product_{primes p} (1+p^(1-s)-p^(-s)). - _R. J. Mathar_, Jan 21 2012a(n) = sum(d|n, phi(d) * mu(d)^2). - _Enrique Pérez Herrero_, Apr 23 2012a(n) = prod(d|n, d^(moebius(n/d))) (see Billal link). - _Michel Marcus_, Jan 06 2015","maple":"with(numtheory); A007947 := proc(n) local i,t1,t2; t1 := ifactors(n)[2]; t2 := mul(t1[i][1],i=1..nops(t1)); end;A007947 := n -> ilcm(op(numtheory[factorset](n))):seq(A007947(i),i=1..69); # _Peter Luschny_, Mar 22 2011A:= n -> convert(numtheory:-factorset(n),`*`):seq(A(n),n=1..100); # _Robert Israel_, Aug 10 2014","mathematica":"rad[n_] := Times @@ (First@# & /@ FactorInteger@ n); Array[rad, 78] (* _Robert G. Wilson v_, Aug 29 2012 *)Table[Last[Select[Divisors[n],SquareFreeQ]],{n,100}] (* _Harvey P. Dale_, Jul 14 2014 *)","prog":"(PARI) a(n) = factorback(factorint(n)[,1]); \\\\ _Andrew Lelechenko_, May 09 2014(MAGMA) [ &*PrimeDivisors(n): n in [1..100] ]; /* _Klaus Brockhaus_, Dec 04 2008 */(Haskell)a007947 = product . a027748_row  -- _Reinhard Zumkeller_, Feb 27 2012(Sage) def A007947(n) : return 1/mul(1/p for p in prime_divisors(n))[A007947(n) for n in (1..60)] # _Peter Luschny_, Jun 10 2012","crossrefs":["Cf. A048803, A007913, A062953, A000188, A019554, A020500, A053462.","Bisection: A099984, A099985."],"keyword":"nonn,easy,nice,mult","offset":"1,2","author":"R. Muller","extensions":["More terms from several people including _David W. Wilson_","Definition expanded by _Jonathan Sondow_, Apr 26 2013"]}