{"formerly":"","seq":"0,1,3,11,58,409,3606,38149,470856,6641793,105398650,1858413061,36044759796,762659322385,17481598316742,431535346662645,11413394655983536,321989729198400385,96515739301398506100,1,-3,11,-58,409,-3606,38149,-470856,6641793,-105398650,1858413061,-36044759796,762659322385,-17481598316742,431535346662645,-11413394655983536,321989729198400385,-9651573930139850610","description":"E.g.f. log(1+x/exp(x)).","comments":"abs(a(n)) is the number of connected functions f:{1,2,...,n}->{1,2,...,n} such that every element is mapped into a recurrent element. Cf. A006153. - _Geoffrey Critzer_, May 24 2012","links":["INRIA Algorithms Project, <a href=\"http://algo.inria.fr/ecs/ecs?searchType=1&amp;service=Search&amp;searchTerms=125\">Encyclopedia of Combinatorial Structures 125</a>"],"formula":"abs(a(n)) is asymptotic to (n-1)!/LambertW(1)^n. - _Vladeta Jovovic_, Jul 12 2007Sequence of absolute values has e.g.f. log(1/(1-x*exp(x))). - _Joerg Arndt_, Apr 30 2011a(n) = (-1)^(n+1)*n!*sum(m=1..n, m^(n-m-1)/(n-m)!). - _Vladimir Kruchinin_, Oct 08 2011","prog":"(PARI) x='x+O('x^66); /* that many terms */egf=1/(1+x/exp(x)); /* = 1 - x + 2*x^2 - 7/2*x^3 + 37/6*x^4 - 87/8*x^5 +... */Vec(serlaplace(egf)) /* show terms */ /* _Joerg Arndt_, Apr 30 2011 */(Maxima)a(n):=(-1)^(n+1)*n!*sum(m^(n-m-1)/(n-m)!,m,1,n); /* _Vladimir Kruchinin_, Oct 08 2011 */(Sage)A009444 = lambda n: (-1)^(n+1)*factorial(n)*sum(m^(n-m-1)/factorial(n-m) for m in (1..n))[A009444(n) for n in (0..9)] # _Peter Luschny_, Jan 18 2016","crossrefs":["Cf. A006153."],"keyword":"sign,easy","offset":"0,3","author":"_R. H. Hardin_","extensions":["Extended with signs by _Olivier Gérard_, Mar 15 1997","Definition corrected by _Joerg Arndt_, Apr 30 2011"]}