{"formerly":"","seq":"4,3,6,9,4,4,7,8,5,2,4,6,7,0,2,1,4,9,4,1,7,2,9,4,5,5,4,1,4,8,1,4,1,0,9,2,2,1,7,3,5,4,1,2,2,4,4,2,2,6,0,9,6,2,5,4,1,2,1,7,1,1,1,7,5,5,9,8,0,6,0,6,1,1,2,4,4,3,2,2,7,8,1,4,5,9,4,0,3,6,5,7,7,4,0,7,9,6,0","description":"Decimal expansion of log(79).","references":["M. Abramowitz and I. A. Stegun, eds., Handbook of Mathematical Functions, National Bureau of Standards Applied Math. Series 55, 1964 (and various reprintings), p. 2."],"links":["Harry J. Smith, <a href=\"/A016702/b016702.txt\">Table of n, a(n) for n = 1..20000</a>","M. Abramowitz and I. A. Stegun, eds., <a href=\"http://www.nrbook.com/abramowitz_and_stegun/\">Handbook of Mathematical Functions</a>, National Bureau of Standards, Applied Math. Series 55, Tenth Printing, 1972 [alternative scanned copy]."],"example":"4.369447852467021494172945541481410922173541224422609625412171117559806... - _Harry J. Smith_, May 24 2009","mathematica":"RealDigits[Log[79],10,120][[1]] (* _Harvey P. Dale_, May 09 2012 *)","prog":"(PARI) { default(realprecision, 20080); x=log(79); for (n=1, 20000, d=floor(x); x=(x-d)*10; write(\"b016702.txt\", n, \" \", d)); } \\\\ _Harry J. Smith_, May 24 2009","crossrefs":["Cf. A016507 Continued fraction. - _Harry J. Smith_, May 24 2009"],"keyword":"nonn,cons","offset":"1,1","author":"_N. J. A. Sloane_"}