{"formerly":"","seq":"1,17,82,273,626,697,2402,4369,6643,5321,14642,3731,28562,20417,51332,69905,83522,112931,130322,85449,196964,124457,279842,179129,391251,242777,538084,46839,707282,218161,923522,1118481,1200644,41761,1503652,604513,1874162","description":"Numerator of sum of -4th powers of divisors of n.","comments":"Sum_{d|n} 1/d^k is equal to sigma_k(n)/n^k. So sequences A017665-A017712 also give the numerators and denominators of sigma_k(n)/n^k for k = 1..24. The power sums sigma_k(n) are in sequences A000203 (k=1), A001157-A001160 (k=2,3,4,5), A013954-A013972 for k = 6,7,...,24. - Ahmed Fares (ahmedfares(AT)my-deja.com), Apr 05 2001","mathematica":"A017671[n_Integer] := Numerator[DivisorSigma[-4, n]]; A017671 /@ Range[100] (* _Vladimir Joseph Stephan Orlovsky_, Jul 21 2011 *)","crossrefs":["Cf. A017672."],"keyword":"nonn,frac","offset":"1,2","author":"_N. J. A. Sloane_"}