{"formerly":"","seq":"1,16384,4782969,268435456,6103515625,39182082048,678223072849,4398046511104,22876792454961,10000000000000,379749833583241,213986410758144,3937376385699289,5556003412779008,5838585205078125","description":"Denominator of sum of -14th powers of divisors of n.","comments":"Sum_{d|n} 1/d^k is equal to sigma_k(n)/n^k. So sequences A017665-A017712 also give the numerators and denominators of sigma_k(n)/n^k for k = 1..24. The power sums sigma_k(n) are in sequences A000203 (k=1), A001157-A001160 (k=2,3,4,5), A013954-A013972 for k = 6,7,...,24. - Ahmed Fares (ahmedfares(AT)my-deja.com), Apr 05 2001","crossrefs":["Cf. A017691."],"keyword":"nonn,frac","offset":"1,2","author":"_N. J. A. Sloane_"}