{"formerly":"","seq":"1,64,729,4096,15625,23328,117649,262144,531441,100000,1771561,497664,4826809,3764768,2278125,16777216,24137569,34012224,47045881,32000000,85766121,56689952,148035889,95551488,244140625,11881376,387420489,240945152,594823321","description":"Denominator of sum of -6th powers of divisors of n.","comments":"Sum_{d|n} 1/d^k is equal to sigma_k(n)/n^k. So sequences A017665-A017712 also give the numerators and denominators of sigma_k(n)/n^k for k = 1..24. The power sums sigma_k(n) are in sequences A000203 (k=1), A001157-A001160 (k=2,3,4,5), A013954-A013972 for k = 6,7,...,24. - Ahmed Fares (ahmedfares(AT)my-deja.com), Apr 05 2001","mathematica":"A017676[n_Integer] := Denominator[DivisorSigma[-6, n]]; A017676 /@ Range[100] (* _Vladimir Joseph Stephan Orlovsky_, Jul 22 2011 *)","crossrefs":["Cf. A017675."],"keyword":"nonn,frac","offset":"1,2","author":"_N. J. A. Sloane_"}