{"formerly":"","seq":"1,2,3,5,6,10,15,17,30,34,51,85,102,170,255,510","description":"Divisors of 510.","comments":"For n > 1, these are also numbers x such that k^m + (k+1)^m + ... + (k+x-1)^m is prime for some k where m is in {16, 32, 64, 128}. - _Derek Orr_, Jun 13 2014","links":["<a href=\"/index/Di#divisors\">Index entries for sequences related to divisors of numbers</a>"],"mathematica":"Divisors[510] (* _Wesley Ivan Hurt_, Jun 14 2014 *)","prog":"(PARI) divisors(510) \\\\ _Derek Orr_, Jun 13 2014","keyword":"nonn,fini,full","offset":"1,2","author":"_N. J. A. Sloane_, Dec 11 1996"}