{"formerly":"","seq":"0,0,5,4,9,4,5,0,5,4,9,4,5,0,5,4,9,4,5,0,5,4,9,4,5,0,5,4,9,4,5,0,5,4,9,4,5,0,5,4,9,4,5,0,5,4,9,4,5,0,5,4,9,4,5,0,5,4,9,4,5,0,5,4,9,4,5,0,5,4,9,4,5,0,5,4,9,4,5,0,5,4,9,4,5,0,5,4,9,4,5,0,5,4,9,4,5,0,5","description":"Decimal expansion of 1/182.","formula":"a(n)=(1/15)*{2*(n mod 6)17*[(n+1) mod 6]-8*[(n+2) mod 6]+7*[(n+3) mod 6]-8*[(n+4) mod 6]+17*[(n+5) mod 6]}-5*[C(2*n,n) mod 2], with n>=0 [From _Paolo P. Lava_, Sep 24 2009]","keyword":"nonn,cons","offset":"0,3","author":"_N. J. A. Sloane_."}