{"formerly":"","seq":"0,0,2,1,0,9,7,0,4,6,4,1,3,5,0,2,1,0,9,7,0,4,6,4,1,3,5,0,2,1,0,9,7,0,4,6,4,1,3,5,0,2,1,0,9,7,0,4,6,4,1,3,5,0,2,1,0,9,7,0,4,6,4,1,3,5,0,2,1,0,9,7,0,4,6,4,1,3,5,0,2,1,0,9,7,0,4,6,4,1,3,5,0,2,1,0,9,7,0","description":"Decimal expansion of 1/474.","formula":"a(n)=(1/169)*{-19*(n mod 13)-19*[(n+1) mod 13]+46*[(n+2) mod 13]+33*[(n+3) mod 13]-19*[(n+4) mod 13]-45*[(n+5) mod 13]+98*[(n+6) mod 13]+33*[(n+7) mod 13]-110*[(n+8) mod 13]+20*[(n+9) mod 13]+20*[(n+10) mod 13]-19*[(n+11) mod 13]+72*[(n+12) mod 13]}-5*[C(2*n,n) mod 2], with n>=0 [From _Paolo P. Lava_, Nov 11 2009]","keyword":"nonn,cons","offset":"0,3","author":"_N. J. A. Sloane_."}