{"formerly":"","seq":"1,28,29,57,86,143,229,372,601,973,1574,2547,4121,6668,10789,17457,28246,45703,73949,119652,193601,313253,506854,820107,1326961,2147068,3474029,5621097,9095126,14716223","description":"Fibonacci sequence beginning 1, 28.","links":["Tanya Khovanova, <a href=\"http://www.tanyakhovanova.com/RecursiveSequences/RecursiveSequences.html\">Recursive Sequences</a>","<a href=\"/index/Rec#order_02\">Index entries for linear recurrences with constant coefficients</a>, signature (1, 1)."],"formula":"G.f.: (1+27*x)/(1-x-x^2). - _Philippe Deléham_, Nov 20 2008a(n) = 28*A000045(n) + A000045(n-1). [_Paolo P. Lava_, May 19 2015]","maple":"with(numtheory): with(combinat): P:=proc(q) local n;for n from 0 to q do print(28*fibonacci(n)+fibonacci(n-1));od; end: P(30); # _Paolo P. Lava_, May 19 2015","mathematica":"a={};b=1;c=28;AppendTo[a, b];AppendTo[a, c];Do[b=b+c;AppendTo[a, b];c=b+c;AppendTo[a, c], {n, 4!}];a (* _Vladimir Joseph Stephan Orlovsky_, Sep 18 2008 *)","keyword":"nonn","offset":"0,2","author":"_N. J. A. Sloane_"}