{"formerly":"","seq":"1,2,4,6,10,16,24,36,56,80,118,174,254,378,554,802,1168,1716,2502,3650,5324,7754,11320,16502,24054,35058,51144,74540,108664,158372,230800,336480,490458,714856,1041910,1518840,2213868","description":"Number of cubefree words of length n on two letters.","links":["Charles R Greathouse IV, <a href=\"/A028445/b028445.txt\">Table of n, a(n) for n = 0..47</a> [copied from Edlin paper]","A. E. Edlin, <a href=\"http://www.math.temple.edu/~anne/cubefree.html\">Cube-free words</a>","Mari Huova, <a href=\"http://www.doria.fi/handle/10024/95677\">Combinatorics on Words. New Aspects on Avoidability, Defect Effect, Equations and Palindromes</a>, Turku Centre for Computer Science, TUCS Dissertations No 172, April 2014.","K. Jarhumaki and J. Shallit, <a href=\"http://arXiv.org/abs/math.CO/0304095\">Polynomial vs Exponential Growth in Repetition-Free Binary Words</a>, arXiv:math/0304095 [math.CO], 2003.","R. Kolpakov, <a href=\"https://cs.uwaterloo.ca/journals/JIS/VOL10/Kolpakov/kolpakov42.html\">Efficient Lower Bounds on the Number of Repetition-free Words</a>, J. Integer Sequences, Vol. 10 (2007), Article 07.3.2.","A. M. Shur, <a href=\"http://dx.doi.org/10.1016/j.cosrev.2012.09.001\">Growth properties of power-free languages</a>, Computer Science Review, Vol. 6 (2012), 187-208.","A. M. Shur, <a href=\"http://arxiv.org/abs/1009.4415\">Numerical values of the growth rates of power-free languages</a>, arXiv:1009.4415 [cs.FL], 2010.","Eric Weisstein's World of Mathematics, <a href=\"http://mathworld.wolfram.com/CubefreeWord.html\">Cubefree Word.</a>"],"formula":"Let L = lim a(n)^(1/n); then L exists since a(n) is submultiplicative, and 1.4575732 < L < 1.4575772869240 (Shur 2010). Empirical: L=1.4575772869237..., i.e. the upper bound is very precise. - _Arseny Shur_, Apr 27 2015","mathematica":"Length/@NestList[DeleteCases[Flatten[Outer[Append, #, {0, 1}, 1], 1], {___, x__, x__, x__, ___}] &, {{}}, 20] (* _Vladimir Reshetnikov_, May 16 2016 *)","crossrefs":["Cf. A007777, A082379, A082380."],"keyword":"nonn,changed","offset":"0,2","author":"Anne Edlin (anne(AT)euclid.math.temple.edu)","extensions":["a(29)-a(36) from _Lars Blomberg_, Aug 22 2013"]}