{"formerly":"","seq":"3,4,5,3,3,16,38,9,75,11,149,186,3,260,297,9,1589,531,131,1475,514,41139,21604940,65359479,170677592,933706818,5378862,806321563,360633274,199660579,3220611916266,63890006966,975514583945,8944083","description":"Values of k associated with A033705.","links":["M. Keith, <a href=\"http://www.cs.uwaterloo.ca/journals/JIS/keith.html\">On Repdigit Polygonal Numbers</a>, J. Integer Sequences, Vol. 1, 1998, #6."],"example":"A033705(1) = 6, and 6 is triangular (3 sides), so a(1)=3.A033705(2) = 9, and 9 is square (4 sides), so a(2)=4.","crossrefs":["Cf. A033705, A033707."],"keyword":"nonn","offset":"1,1","author":"Mike Keith (domnei(AT)aol.com)"}