{"formerly":"","seq":"1,1,1,1,2,3,2,4,9,16,3,9,26,67,125,6,20,75,251,680,1296,11,48,214,888,3135,8716,16807","description":"Triangle of number of node labeled trees by number of nodes and number of labels.","references":["J. Riordan, An Introduction to Combinatorial Analysis, p. 138."],"links":["<a href=\"/index/Tra#trees\">Index entries for sequences related to trees</a>"],"formula":"Reference gives generating function.","crossrefs":["Cf. A034799."],"keyword":"nonn,tabl,more","offset":"0,5","author":"_N. J. A. Sloane_."}