{"formerly":"","seq":"0,0,0,0,0,0,0,0,0,0,0,0,0,0,0,0,0,0,0,0,0,0,0,0,0,0,0,0,0,0,0,0,0,0,0,0,4,6,24,55,144,306,722,1508,3299,6844,14472,29909,62712,130290,273986,576333","description":"Multiplicity of highest weight (or singular) vectors associated with character chi_70 of Monster module.","references":["K. Harada and M. L. Lung, Modular forms associated with the Monster module, pp. 59-83 of The Monster and Lie Algebras, de Gruyter, 1998."],"keyword":"nonn","offset":"1,37","author":"_N. J. A. Sloane_."}