{"formerly":"","seq":"1,1,0,1,1,0,0,1,1,1,2,0,0,0,0,1,0,1,2,1,0,2,0,0,1,0,0,0,2,0,2,1,0,0,0,1,0,2,0,1,2,0,0,2,1,0,0,0,1,1,0,0,0,0,2,0,0,2,2,0,2,2,0,1,0,0,0,0,0,0,2,1,0,0,0,2,0,0,2,1,1,2,0,0,0,0,0,2,2,1,0,0,0,0,2,0,0,1,2,1,2,0,0,0,0","description":"Coefficients in expansion of Dirichlet series Product_p (1-(Kronecker(m,p)+1)*p^(-s)+Kronecker(m,p)*p^(-2s))^(-1) for m = 20.","comments":"Also number of divisors of n which end in 1 or 9 minus number of divisors of n which end in 3 or 7. E.g. a(98)=2-1=1 since divisors of 98 are: 1 and 49 counting +1 each; 2, 14 and 98 counting 0 each; and 7 counting -1. - _Henry Bottomley_, Jul 08 2003","links":["MathNerds, <a href=\"http://www.mathnerds.com/best/DivisorExcess/index.aspx\">An Excess of Divisors</a>."],"maple":"a:= proc(n) local D,d; D:= map(`modp`,convert(numtheory:-divisors(n),list),10);      numboccur(1,D) + numboccur(9,D) - numboccur(3,D) - numboccur(7,D);end proc:seq(a(n),n=1..1000); # _Robert Israel_, Sep 22 2014","prog":"(PARI) m=20; direuler(p=2,101,1/(1-(kronecker(m,p)*(X-X^2))-X))","crossrefs":["Cf. A083911, A083913, A083917, A083919."],"keyword":"nonn","offset":"1,11","author":"_N. J. A. Sloane_.","extensions":["More terms from _Henry Bottomley_, Jul 08 2003"]}