{"formerly":"","seq":"1,3,1,7,1,3,1,15,1,3,1,7,1,3,1,31,1,3,1,7,1,3,1,15,1,3,1,7,1,3,1,63,1,3,1,7,1,3,1,15,1,3,1,7,1,3,1,31,1,3,1,7,1,3,1,15,1,3,1,7,1,3,1,127,1,3,1,7,1,3,1,15,1,3,1,7,1,3,1,31,1,3,1,7,1,3,1,15,1,3,1,7,1,3,1,63,1,3","description":"Let k be highest power of 2 dividing n (A006519); a(n) = 2^(k+1)-1.","comments":"n XOR n-1, i.e., nim-sum of a pair of consecutive numbers.Denominator of quotient sigma(2*n)/sigma(n). - _Labos Elemer_, Nov 04 2003a(n) = the Towers of Hanoi disc moved at the n-th move, using standard moves with discs labeled (1, 3, 7, 15,...) starting from top (smallest = 1). - _Gary W. Adamson_, Oct 26 2009Equals row sums of triangle A168312. - _Gary W. Adamson_, Nov 22 2009a(n) = A086799(2*n) - 2*n. - _Reinhard Zumkeller_, Aug 07 2011In the binary expansion of n, delete everything left of the rightmost 1 bit, and set all bits to the right of it. - _Ralf Stephan_, Aug 22 2013Every finite sequence of positive integers summing to n may be termwise dominated by a subsequence of the first n values in this sequence [see Bannister et al., 2013]. - _David Eppstein_, Aug 31 2013","links":["R. Zumkeller, <a href=\"/A038712/b038712.txt\">Table of n, a(n) for n = 1..10000</a>","M. J. Bannister, Z. Cheng, W. E. Devanny, and D. Eppstein, <a href=\"http://arxiv.org/abs/1308.0403\">Superpatterns and universal point sets</a>, 21st Int. Symp. Graph Drawing, 2013, arXiv:1308.0403","Klaus Brockhaus, <a href=\"/A038712/a038712.gif\">Illustration of A038712 and A080277</a>","D. Eppstein, <a href=\"http://11011110.livejournal.com/273608.html\">1317131 and majorization by subsequences</a>","R. Stephan, <a href=\"/somedcgf.html\">Some divide-and-conquer sequences ...</a>","R. Stephan, <a href=\"/A079944/a079944.ps\">Table of generating functions</a>","R. Stephan, <a href=\"http://arXiv.org/abs/math.CO/0307027\">Divide-and-conquer generating functions. I. Elementary sequences</a>","<a href=\"/index/Ni#Nimsums\">Index entries for sequences related to Nim-sums</a>","<a href=\"/index/Bi#binary\">Index entries for sequences related to binary expansion of n</a>"],"formula":"a(n) = A110654(n-1) XOR A008619(n). - _Reinhard Zumkeller_, Feb 05 2007a(n) = 2^A001511(n)-1 = 2*A006519(n)-1 = 2^(A007814(n)+1)-1Multiplicative with a(2^e) = 2^(e+1)-1, a(e^p) = 1, p>2. - _Vladeta Jovovic_, Nov 06 2001Sum_{n>0} a(n)*x^n/(1+x^n) = Sum_{n>0} x^n/(1-x^n). Inverse Moebius transform of A048298. - _Vladeta Jovovic_, Jan 02 2003G.f.: Sum(k>=0, 2^k*x^2^k/(1-x^2^k)). a(2*n+1) = 1, a(2*n) = 2*a(n)+1. - _Ralf Stephan_, Jun 15 2003Equals A130093 * [1, 2, 3,...]. - _Gary W. Adamson_, May 13 2007Sum(i=1,n, (-1)^A000120(n-i)*a(i))=(-1)^(A000120(n)-1)*n. - _Vladimir Shevelev_, Mar 17 2009Dirichlet g.f. zeta(s)/(1-2^(1-s)). - _R. J. Mathar_, Mar 10 2011a((2*n-1)*2^p) = 2^(p+1)-1, p >= 0. - _Johannes W. Meijer_, Feb 01 2013a(n) = A000225(A001511(n)). - _Omar E. Pol_, Aug 31 2013","example":"a(6) = 3 because 110 XOR 101 = 11 base 2 = 3.","maple":"nmax:=98: for p from 0 to ceil(simplify(log[2](nmax))) do for n from 1 to ceil(nmax/(p+2)) do a((2*n-1)*2^p) := 2^(p+1)-1 od: od: seq(a(n), n=1..nmax); # _Johannes W. Meijer_, Feb 01 2013","mathematica":"Table[Denominator[DivisorSigma[1, 2*n]/DivisorSigma[1, n]], {n, 1, 128}]Table[BitXor[(n + 1), n], {n, 0, 100}] (* _Vladimir Joseph Stephan Orlovsky_, Jul 19 2011 *)","prog":"(C) int a(int n) { return n ^ (n-1); } // _Russ Cox_, May 15 2007(Haskell)import Data.Bits (xor)a038712 n = n `xor` (n - 1) :: Integer  -- _Reinhard Zumkeller_, Apr 23 2012(PARI) vector(66,n,bitxor(n,n+1)) \\\\ _Joerg Arndt_, Sep 01 2013","crossrefs":["A038713 translated from binary, diagonals of A003987 on either side of main diagonal.","Cf. A062383. Partial sums give A080277.","Bisection of A089312. Cf. A088837.","a(n)-1 is exponent of 2 in A089893(n).","Cf. A130093.","This is Guy Steele's sequence GS(6, 2) (see A135416).","Cf. A168312, A220466."],"keyword":"easy,nonn,mult","offset":"1,2","author":"_Henry Bottomley_, May 02 2000","extensions":["Definition corrected by _N. J. A. Sloane_, Sep 07 2015 at the suggestion of _Marc LeBrun_."]}