{"formerly":"","seq":"22,3,2,2,5,6,5,2,2,3,44,3,2,2,5,6,5,2,2,3,44,3,2,2,5,6,5,2,2,3,44,3,2,2,5,6,5,2,2,3,44,3,2,2,5,6,5,2,2,3,44,3,2,2,5,6,5,2,2,3,44,3,2,2,5,6,5,2,2,3,44,3,2,2,5,6,5,2,2,3,44,3,2,2,5,6,5,2,2,3","description":"Continued fraction for sqrt(497).","links":["<a href=\"/index/Con#confC\">Index entries for continued fractions for constants</a>"],"formula":"a(n)=(1/450)*{-1771*(n mod 10)+29*[(n+1) mod 10]+74*[(n+2) mod 10]+209*[(n+3) mod 10]+119*[(n+4) mod 10]+29*[(n+5) mod 10]-61*[(n+6) mod 10]+74*[(n+7) mod 10]+119*[(n+8) mod 10]+1919*[(n+9) mod 10]}-22*[C(2*n,n) mod 2], with n>=0 [From _Paolo P. Lava_, May 13 2009]","maple":"with(numtheory): Digits := 300: convert(evalf(sqrt(497)),confrac);","mathematica":"ContinuedFraction[Sqrt[497],100] (* _Harvey P. Dale_, Jan 13 2012 *)","keyword":"nonn,cofr,easy,less","offset":"0,1","author":"_N. J. A. Sloane_."}