{"formerly":"","seq":"31,6,4,1,1,1,2,5,3,2,12,31,12,2,3,5,2,1,1,1,4,6,62,6,4,1,1,1,2,5,3,2,12,31,12,2,3,5,2,1,1,1,4,6,62,6,4,1,1,1,2,5,3,2,12,31,12,2,3,5,2,1,1,1,4,6,62,6,4,1,1,1,2,5,3,2,12,31,12,2,3,5,2,1,1,1","description":"Continued fraction for sqrt(971).","links":["<a href=\"/index/Con#confC\">Index entries for continued fractions for constants</a>"],"maple":"with(numtheory): Digits := 300: convert(evalf(sqrt(971)),confrac);","keyword":"nonn,cofr,easy","offset":"0,1","author":"_N. J. A. Sloane_."}