{"formerly":"","seq":"17,1,4,1,34,1,4,1,34,1,4,1,34,1,4,1,34,1,4,1,34,1,4,1,34,1,4,1,34,1,4,1,34,1,4,1,34,1,4,1,34,1,4,1,34,1,4,1,34,1,4,1,34,1,4,1,34,1,4,1,34,1,4,1,34,1,4,1,34,1,4,1,34,1,4,1,34,1,4,1,34,1,4,1","description":"Continued fraction for sqrt(318).","links":["<a href=\"/index/Con#confC\">Index entries for continued fractions for constants</a>"],"formula":"a(n)=(1/12)*{-79*(n mod 4)+29*[(n+1) mod 4]+11*[(n+2) mod 4]+119*[(n+3) mod 4]}-17*[C(2*n,n) mod 2], with n>=0 [From _Paolo P. Lava_, Apr 27 2009]","maple":"with(numtheory): Digits := 300: convert(evalf(sqrt(318)),confrac);","mathematica":"ContinuedFraction[Sqrt[318],100] (* _Harvey P. Dale_, Nov 04 2012 *)","keyword":"nonn,cofr,easy","offset":"0,1","author":"_N. J. A. Sloane_."}