{"formerly":"","seq":"30,31,61,1190,1251,7445,45921,53366,99287,152653,251940,656533,908473,1565006,2473479,4038485,26704389,137560430,164264819,3258591991,3422856810,6681448801,404309784870","description":"Numerators of continued fraction convergents to sqrt(931).","links":["Vincenzo Librandi, <a href=\"/A042800/b042800.txt\">Table of n, a(n) for n = 0..200</a>"],"mathematica":"Numerator[Convergents[Sqrt[931], 30]] (* _Vincenzo Librandi_, Dec 05 2013 *)","crossrefs":["Cf. A042801."],"keyword":"nonn,cofr,frac,easy","offset":"0,1","author":"_N. J. A. Sloane_."}