{"formerly":"","seq":"24,25,49,123,172,639,1450,2089,3539,5628,9167,14795,68347,83142,484057,1535313,14301874,15837187,30139061,467923102,498062163,3456296080,41973615123,255297986818,297271601941","description":"Numerators of continued fraction convergents to sqrt(604).","links":["Vincenzo Librandi, <a href=\"/A042158/b042158.txt\">Table of n, a(n) for n = 0..200</a>"],"mathematica":"Numerator[Convergents[Sqrt[604], 30]] (* _Vincenzo Librandi_, Nov 18 2013 *)","crossrefs":["Cf. A042159."],"keyword":"nonn,cofr,frac,easy,less","offset":"0,1","author":"_N. J. A. Sloane_."}