{"formerly":"","seq":"0,0,0,0,1,0,0,1,1,0,0,0,0,0,0,0,1,0,0,1,0,0,0,0,1,0,0,0,0,1,0,0,0,0,1,0,0,0,0,1,0,1,0,0,0,0,0,1,1,1,1,1,1,0,0,0,0,1,2,1,2,1,2,1,0,00,0,0,0,1,0,0,1,1,0,0,0,0,0,0,0,1,0,0,1,0,0,0,0,-1,0,0,0,0,1,0,0,0,0,1,0,0,0,0,-1,0,-1,0,0,0,0,0,-1,-1,-1,-1,-1,-1,0,0,0,0,-1,-2,-1,-2,-1,-2,-1,0,0","description":"Array a(m,n) = pi(m+n)-pi(m)-pi(n) read by antidiagonals, where pi() = A000720 (m,n >= 0).","comments":"A212210-A212213 are the preferred versions of this array.","example":"Beginning of array is0 0 0 0 0 0 0 0 ...0 1 1 0 1 0 1 0 ...0 1 0 0 0 0 -1 ...0 0 0 -1 0 -1 -1 ...","crossrefs":["Cf. A047886, A212210-A212213, A000720."],"keyword":"sign,tabl,easy","offset":"0,59","author":"_N. J. A. Sloane_."}