{"formerly":"","seq":"60,93,41,51,87,81,86,510,401,501,516,705,801,701,761,725,701,840,600,534,443,824,543,615","description":"Largest factor i of any factorization used in the definition of A014575(n).","references":["C. A. Pickover, \"Vampire Numbers.\" Ch. 30 in Keys to Infinity. New York: Wiley, pp. 227-231, 1995."],"links":["R. J. Mathar, <a href=\"/A048934/b048934.txt\">Table of n, a(n) for n = 1..78</a>","Eric Weisstein's World of Mathematics, <a href=\"http://mathworld.wolfram.com/VampireNumber.html\">Vampire Number.</a>"],"crossrefs":["Cf. A014575, A048933, ..., A048939."],"keyword":"nonn,base,more","offset":"1,1","author":"_Eric W. Weisstein_","extensions":["Edited by _N. J. A. Sloane_, Jan 03 2009"]}