{"formerly":"","seq":"1,2,12,48,152,424,1096,2696,6408,14856,33800,75784,167944,368648,802824,1736712,3735560,7995400,17039368,36175880,76546056,161480712,339738632,713031688,1493172232,3120562184,6509559816,13555990536","description":"2^(n-1)*(8*n-14)+8.","comments":"a(n) = T(7, n), array T given by A048494.","links":["Vincenzo Librandi, <a href=\"/A048501/b048501.txt\">Table of n, a(n) for n = 0..2000</a>","<a href=\"/index/Rec#order_03\">Index entries for linear recurrences with constant coefficients</a>, signature (5, -8, 4)."],"mathematica":"Table[2^(n-1) (8n-14)+8,{n,0,30}] (* or *) LinearRecurrence[{5,-8,4},{1,2,12},30] (* _Harvey P. Dale_, Nov 22 2014 *)","prog":"(MAGMA) [2^(n-1)*(8*n-14)+8 : n in [0..30]]; // Vincenzo Librandi, Sep 25 2011","keyword":"nonn,easy","offset":"0,2","author":"_Clark Kimberling_","extensions":["Formula from _Ralf Stephan_, Jan 15 2004"]}