{"formerly":"","seq":"1,5,5,7,4,0,7,7,2,4,6,5,4,9,0,2,2,3,0,5,0,6,9,7,4,8,0,7,4,5,8,3,6,0,1,7,3,0,8,7,2,5,0,7,7,2,3,8,1,5,2,0,0,3,8,3,8,3,9,4,6,6,0,5,6,9,8,8,6,1,3,9,7,1,5,1,7,2,7,2,8,9,5,5,5,0,9,9,9,6,5,2,0,2,2,4,2,9,8","description":"Decimal expansion of tan 1.","references":["Mohammad K. Azarian, Forty-Five Nested Equilateral Triangles and cosecant of 1 degree, Problem 813, College Mathematics Journal, Vol. 36, No. 5, November 2005, p. 413-414. Solution published in Vol. 37, No. 5, November 2006, pp. 394-395."],"links":["Harry J. Smith, <a href=\"/A049471/b049471.txt\">Table of n, a(n) for n = 1..20000</a>"],"example":"1.5574077246549022305...","prog":"(PARI) { default(realprecision, 20080); x=tan(1); for (n=1, 20000, d=floor(x); x=(x-d)*10; write(\"b049471.txt\", n, \" \", d)); } \\\\ _Harry J. Smith_, Jun 13 2009","crossrefs":["Cf. A093178 Continued fraction. A009001. - _Harry J. Smith_, Jun 13 2009"],"keyword":"cons,easy,nonn","offset":"1,2","author":"Albert du Toit (dutwa(AT)intekom.co.za), _N. J. A. Sloane_"}