{"formerly":"","seq":"1,1,1,2,1,3,1,4,1,5,1,1,1,7,1,8,1,9,1,5,1,11,1,6,1,13,1,7,1,1,1,16,1,17,1,3,1,19,1,2,1,7,1,11,1,23,1,4,1,25,1,13,1,27,1,1,1,29,1,15,1,31,1,32,1,11,1,17,1,5,1,18,1,37,1,19,1,39,1,4,1,41,1,1,1,43,1,11,1,1,1,23","description":"a(n) = n / GCD(n,C(n,floor(n/2))).","example":"For odd n, a(n) = 1, for even n, a(n) is either n/2 or smaller, e.g. for n = 12, GCD(12, C(12, 6)) = GCD(12, 924) = 12 so a(12) = 1.","maple":"swing := n -> n!/iquo(n,2)!^2: seq(n/igcd(n,swing(n)),n=1..92); # _Peter Luschny_, May 16 2013","mathematica":"Flatten[Table[{1, n/GCD[n, Binomial[n, n/2]]}, {n, 2, 100, 2}]] (* _Alonso del Arte_, May 17 2013 *)","crossrefs":["Cf. A001405, A057815, A014973."],"keyword":"nonn","offset":"1,4","author":"_Labos Elemer_, Nov 13 2000","extensions":["Changed offset to 1, _Peter Luschny_, May 16 2013"]}