{"formerly":"","seq":"0,1,0,1,1,1,2,3,4,1,5,9,14,6,1,14,28,48,27,8,1,42,90,165,110,44,10,1,132,297,572,429,208,65,12,1,429,1001,2002,1638,910,350,90,14,1,1430,3432,7072,6188,3808,1700,544,119,16,1","description":"T(n,k)=M(2n-1,n-1,k-1), 0<=k<=n, n >= 0, where M(p,q,r)=number of upright paths from (0,0) to (p,p-q) that meet the line y=x-r and do not rise above it.","comments":"Let V=(e(1),...,e(n)) consist of q 1's and p-q 0's; let V(h)=(e(1),...,e(h)) and m(h)=(#1's in V(h))-(#0's in V(h)) for h=1,...,n. Then M(p,q,r)=number of V having r=max{m(h)}.First 6 columns of T are A000108, A000245, A002057, A003517, A003518, A003519.","references":["B. A. Bondarenko, Generalized Pascal Triangles and Pyramids (in Russian), FAN, Tashkent, 1990, ISBN 5-648-00738-8. English translation published by Fibonacci Association, Santa Clara Univ., Santa Clara, CA, 1993; see p. 29.","E. Deutsch and L. Shapiro, A survey of the Fine numbers, Discrete Math., 241 (2001), 241-265."],"links":["R. K. Guy, Catwalks, Sandsteps and Pascal Pyramids, <a href=\"http://www.cs.uwaterloo.ca/journals/JIS/index.html\">J. Integer Seqs., Vol. 3 (2000), #00.1.6</a>"],"formula":"For n>0: Sum_{k>=0} T(n, k)= binomial(2*n-1, n); see A001700. Sum_{k>=1} (-1)^k*T(n, k) = 0 . - _Philippe Deléham_, Feb 13 2004T(n, k) = 0 if n<k; T(0, 0)= 0, T(n, 0)= A000108(n-1) for n>0; T(n, 1)= sum_{j>=0} T(n-1-j, 0)*A000108(j); T(n, 2)= sum_{j>=0} T(n-j, 1)*A000108(j+1); for k>2, T(n, k)= sum_{j>=0} T(n-1-j, k-1)*A000108(j+1) . For the column k=0, G.f.: x*C(x); for the column k=1, G.f.: x*C(x)*(C(x)-1); for the column k, k>1, G.f.: x*C(x)^2*(C(x)-1)^(k-1); where C(x)= sum_{n>=0} A000108(n)*x^n is G.f. for Catalan numbers, A000108 . - _Philippe Deléham_, Feb 13 2004","example":"Rows: {0}; {1,0}; {1,1,1}; ...","crossrefs":["{M(2n, n, k)} is given by A039599. {M(2n+1, n+1, k+1)} is given by A039598."],"keyword":"nonn,tabl","offset":"0,7","author":"_Clark Kimberling_"}