{"formerly":"","seq":"0,1,0,1,1,2,3,6,12,25,53,114,257,567,1294,2944,6790,15693,36598,85578,201299","description":"Number of unlabeled mobiles with cycles of length at least 3.","links":["Robert Israel, <a href=\"/A052523/b052523.txt\">Table of n, a(n) for n = 0..2234</a>","INRIA Algorithms Project, <a href=\"http://algo.inria.fr/ecs/ecs?searchType=1&amp;service=Search&amp;searchTerms=91\">Encyclopedia of Combinatorial Structures 91</a>"],"maple":"spec := [S,{S=Union(B,Z),B=Cycle(S,3 <= card)},unlabeled]: seq(combstruct[count](spec, size=n), n=0..20);","keyword":"easy,nonn","offset":"0,6","author":"encyclopedia(AT)pommard.inria.fr, Jan 25 2000"}