{"formerly":"","seq":"1,7,28,85,218,499,1053,2092,3970,7272,12958,22596,38739,65535,109714,182185,300620,493635,807555,1317360,2144396,3485032,5657028,9174560,14869613,24088399,39009168,63156437,102233030,165466347,267786673","description":"A second-order recursive sequence.","references":["A. H. Beiler, Recreations in the Theory of Numbers, Dover, N.Y., 1964, pp. 194-196.","A. F. Horadam,Special Properties of the Sequence W(n){a,b; p,q}, Fib. Quart., Vol. 5, No. 5(1967), pp. 424-434.","A. K. Whitford, Binet's Formula Generalized, Fib. Quart., Vol. 15, No. 1(1977), pp. 21, 24, 29."],"links":["Vincenzo Librandi, <a href=\"/A054469/b054469.txt\">Table of n, a(n) for n = 0..1000</a>","<a href=\"/index/Rec#order_07\">Index entries for linear recurrences with constant coefficients</a>, signature (6,-14,15,-5,-4,4,-1)."],"formula":"a(n)=a(n-1)+a(n-2)+(n+2)*C(n+3, 3)/2=a(n-1)+a(n-2)+(n+1)(n+2)^2(n+3)/12; a(-n)=0.a(n)=sum{C(n+5-i, n+2-2i); i=1 to [(n+2)/2]}+2*sum{C(n+5-i, n+1-2i); i=1 to [(n+1)/2]; where [x]=greatest integer in x.G.f.: (x+1) / ((x-1)^5*(x^2+x-1)). - _Colin Barker_, Jun 11 2013","mathematica":"RecurrenceTable[{a[0]==1,a[1]==7,a[n]==a[n-1]+a[n-2]+(n+2) Binomial[ n+3,3]/2},a,{n,30}] (* _Harvey P. Dale_, Sep 22 2013 *)CoefficientList[Series[(x + 1)/((x - 1)^5 (x^2 + x - 1)), {x, 0, 40}], x] (* _Vincenzo Librandi_, Sep 23 2013 *)","crossrefs":["Cf. A001891, A001911.","Right-hand column 11 of triangle A011794."],"keyword":"easy,nonn","offset":"0,2","author":"_Barry E. Williams_, Mar 31 2000"}