{"formerly":"","seq":"5,1667,7517,34853363,116755331881,20537111057,373","description":"The first nontrivial (k>n+2) palindromic prime in both bases n and n+2.","comments":"a(9) > 5.5*10^22, a(10) = 181, a(11) = 161292069901, a(12) = 773. - _Giovanni Resta_, Feb 28 2013","example":"a(3) = 1667 because it is the first prime > 5 which is a palindrome in both base 3 and 5.","mathematica":"f[n_] := Block[{k = n + 3}, While[a = IntegerDigits[k, n]; b = IntegerDigits[k, n + 2]; ! PrimeQ[k] || a != Reverse[a] || b != Reverse[b], k++]; k]; Do[ Print[{n, f[n] // Timing}], {n, 2, 10}]","crossrefs":["Cf. A048269."],"keyword":"nonn,base,more","offset":"2,1","author":"_Robert G. Wilson v_, Sep 16 2000","extensions":["a(6)-a(8) from _Giovanni Resta_, Feb 28 2013"]}