{"formerly":"","seq":"1,1,2,4,9,21,60,208,1418,381448","description":"Number of nonisomorphic loopless matroids on n unlabeled points.","links":["W. M. B. Dukes, <a href=\"http://www.stp.dias.ie/~dukes/matroid.html\">Tables of matroids</a>","W. M. B. Dukes, <a href=\"http://www.stp.dias.ie/~dukes/phd.html\">Counting and Probability in Matroid Theory</a>, Ph.D. Thesis, Trinity College, Dublin, 2000.","Gordon Royle and Dillon Mayhew, <a href=\"http://people.csse.uwa.edu.au/gordon/matroid-integer-sequences.html\">9-element matroids</a>","<a href=\"/index/Mat#matroid\">Index entries for sequences related to matroids</a>"],"crossrefs":["Row sums of A058716."],"keyword":"nonn,nice","offset":"0,3","author":"_N. J. A. Sloane_, Dec 31 2000","extensions":["a(9) from Gordon Royle, Dec 23 2006"]}