{"formerly":"","seq":"1,11,21,55,110,285,450,1001,1605,2936,4740,8271,125711,-11,-21,-55,-110,-285,-450,-1001,-1605,-2936,-4740,-8271,-12571","description":"McKay-Thompson series of class 12a for Monster.","references":["D. Ford, J. McKay and S. P. Norton, More on replicable functions, Commun. Algebra 22, No. 13, 5175-5193 (1994)."],"links":["<a href=\"/index/Mat#McKay_Thompson\">Index entries for McKay-Thompson series for Monster simple group</a>"],"example":"T12a = 1/q - 11*q - 21*q^3 - 55*q^5 - 110*q^7 - 285*q^9 - 450*q^11 - ...","crossrefs":["Cf. A000521, A007240, A014708, A007241, A007267, A045478, etc."],"keyword":"sign","offset":"-1,2","author":"_N. J. A. Sloane_, Nov 27 2000"}