{"formerly":"","seq":"0,1,0,1,2,3,2,3,0,1,0,1,2,3,2,3,4,5,4,5,6,7,6,7,4,5,4,5,6,7,6,7,0,1,0,1,2,3,2,3,0,1,0,1,2,3,2,3,4,5,4,5,6,7,6,7,4,5,4,5,6,7,6,7,8,9,8,9,10,11,10,11,8,9,8,9,10,11,10,11,12,13,12,13,14,15,14,15,12,13,12,13,14","description":"Index of first half of decomposition of integers into pairs based on A000695.","comments":"One coordinate of a recursive non-self intersecting walk on the square lattice Z^2.","links":["Peter Kagey, <a href=\"/A059905/b059905.txt\">Table of n, a(n) for n = 0..8192</a>"],"formula":"n = A000695(a(n))+2*A000695(A059906(n))To get a(n), write n as Sum b_j*2^j, then a(n)=Sum b_(2j)*2^j. - _Vladimir Shevelev_, Nov 13 2008a(n) = Sum_k>=0 {A030308(n,k)*A077957(k)}. - _Philippe Deléham_, Oct 18 2011G.f.: (1-x)^(-1) * Sum_{j>=0} 2^j*x^(2^j)/(1+x^(2^j)). - _Robert Israel_, Aug 12 2015","example":"A000695(a(14))+2*A000695(A059906(14)) = A000695(2)+2*A000695(3) = 4+2*5 = 14.If n=27, then b_0=1, b_1=1, b_2=0, b_3=1, b_4=1. Therefore a(n)=b_0+b_2*2+b_4*2^2=5. - _Vladimir Shevelev_, Nov 13 2008","maple":"f:= proc(n) local L; L:= convert(n,base,2); add(L[2*i+1]*2^i,i=0..floor((nops(L)-1)/2)) end;map(f, [$0..256]); # _Robert Israel_, Aug 12 2015","prog":"(Ruby)def a(n)  (0..n.bit_length/2).to_a.map { |i| (n >> 2 * i & 1) << i}.reduce(:+)end # _Peter Kagey_, Aug 12 2015","crossrefs":["Cf. A000695, A059906."],"keyword":"easy,nonn,look","offset":"0,5","author":"_Marc LeBrun_, Feb 07 2001"}