{"formerly":"","seq":"1,1,2,1,2,1,3,2,3,1,3,1,3,2,4,1,3,1,4,3,3,1,4,2,3,3,5,1,5,1,5,3,3,3,5,1,3,3,5,1,4,1,5,4,3,1,5,2,5,3,5,1,4,3,6,3,3,1,7,1,3,4,6,3,5,1,5,3,6,1,6,1,3,3,5,3,5,1,7,4,3,1,6,3,3,3,7,1,7,2,5,3,3,3,6,1,5,4,6,1,5,1,7,5,3","description":"Number of distinct differences between consecutive divisors of n (ordered by size).","comments":"Number of all differences for n is d(n)-1 = A000005(n)-1. Increments are not necessarily different, so a(n)<=d(n)-1.","links":["Reinhard Zumkeller, <a href=\"/A060682/b060682.txt\">Table of n, a(n) for n = 2..10000</a>","A. Balog, P. Erdős and G. Tenenbaum, <a href=\"http://dx.doi.org/10.1007/978-1-4612-3464-7_6\">On Arithmetic Functions Involving Consecutive Divisors</a>, In: Analytical Number Theory, pp. 77-90, Birkhauser, Basel, 1990."],"example":"For n=70, divisors={1,2,5,7,10,14,35,70}; differences={1,3,2,3,4,21,35}; a(70) = number of distinct differences = 6.","mathematica":"a[n_ ] := Length[Union[Drop[d=Divisors[n], 1]-Drop[d, -1]]]","prog":"(Haskell)import Data.List (nub, genericLength)a060682 = genericLength . nub . a193829_row-- _Reinhard Zumkeller_, Jun 25 2015","crossrefs":["Cf. A000005, A060680, A060681, A060683.","Cf. A193829."],"keyword":"nonn","offset":"2,3","author":"_Labos Elemer_, Apr 19 2001","extensions":["Edited by _Dean Hickerson_, Jan 22 2002"]}