{"formerly":"","seq":"0,1,11,111,12,2,21,211,2111,13,3,31,311,3111,312,32,321,3211,32111,313,33,331,3311,33111,3312,332,3321,33211,332111,3313,333,3331,33311,333111,33312,3332,33321,333211,3332111,33313,34,341,3411,34111,3412","description":"Roman numerals written using 1 for I, 2 for V, 3 for X, 4 for L, 5 for C, 6 for D, 7 for M.","comments":"The initial a(0) = 0 is purely conventional._Daniel Forgues_, Jan 16 2015 (Start)Roman numerals written using 0 for N, 1 for I, ...The Romans did not have 0 as a number, which is why there was no year zero (1 B.C. is followed by 1 A.D.).The initial \"N\" (nulla, meaning \"nothing\") was used as a zero symbol in a table of Roman numerals by Bede or his colleague around 725. (End)","links":["Reinhard Zumkeller, <a href=\"/A061493/b061493.txt\">Table of n, a(n) for n = 1..3999</a>","Gerard Schildberger, <a href=\"/A006968/a006968.txt\">The first 3999 numbers in Roman numerals</a>","Eric Weisstein's World of Mathematics, <a href=\"http://mathworld.wolfram.com/RomanNumerals.html\">Roman Numerals</a>","Wikipedia, <a href=\"http://en.wikipedia.org/wiki/Roman_numerals\">Roman numerals</a>","Wikipedia, <a href=\"http://en.wikipedia.org/wiki/0_%28number%29#Greeks_and_Romans\">0 (number)#Greeks and Romans</a>"],"formula":"a(n)=i <=> A003587(i)=n, for i in {1,...,7}, i.e., A061493 is a left inverse of A003587 on {1,...,7}. - _M. F. Hasler_, Jan 12 2015","example":"a(14) = 312 because 14 = XIV in Roman, and I,V,X are coded as 1,2,3 respectively.a(66)= 4321, LXVI is 50+10+5+1= 66, a(44)=3412, XLIV is -10+50-1+5= 44","prog":"(Haskell)a061493 n = read $ r 1 [] n :: Integer where  r _ roms 0 = roms  r p roms z = case p of    1 -> r 2 (d '1' '2' '3' m) z'    2 -> r 3 (d '3' '4' '5' m ++ roms) z'    3 -> r 4 (d '5' '6' '7' m ++ roms) z'    4 -> replicate z '7' ++ roms    where (z',m) = divMod z 10  d i j k c =    [[],[i],[i,i],[i,i,i],[i,j],[j],[j,i],[j,i,i],[j,i,i,i],[i,k]] !! c-- _Reinhard Zumkeller_, Apr 14 2013(PARI) {A061493(n,s=\"\",c=[1000,7,900,57,500,6,400,56,100,5,90,35,50,4,40,34,10,3,9,13,5,2,4,12,1,1])= forstep(i=1,#c,2,while(n>=c[i],n-=c[i];s=Str(s,c[i+1])));eval(s)} \\\\ _M. F. Hasler_, Jan 11 2015","crossrefs":["Cf. A006968, A002963, A003587, A036787, A057226.","Cf. A036746, A036786, A036788, A160676, A160677, A199921."],"keyword":"easy,nonn,base","offset":"0,3","author":"_Frank Ellermann_, Jun 12 2001"}